{ 
    "name":"",
    "code":"",
    "regions": [
        {"name":"", "code":"", "regionFilter":""},
        {"name":"", "code":"", "regionFilter":""},
        {"name":"", "code":"", "regionFilter":""},
        {"name":"", "code":"", "regionFilter":""},
        {"name":"", "code":"", "regionFilter":""},
        {"name":"", "code":"", "regionFilter":""},
        {"name":"", "code":"", "regionFilter":""},
        {"name":"", "code":"", "regionFilter":""},
        {"name":"", "code":"", "regionFilter":""},
        {"name":"", "code":"", "regionFilter":""}
    ]
}

{ 
    "name":"",
    "code":"",
    "regions": [

    ]
}